cydantic/__init__.py
cydantic/main.py
cydantic-0.1.0.dist-info/LICENSE
cydantic-0.1.0.dist-info/METADATA
cydantic-0.1.0.dist-info/WHEEL
cydantic-0.1.0.dist-info/entry_points.txt
cydantic-0.1.0.dist-info/RECORD
